pyhyperminhash-0.1.5.dist-info/METADATA
pyhyperminhash-0.1.5.dist-info/WHEEL
pyhyperminhash-0.1.5.dist-info/licenses/LICENSE
pyhyperminhash/__init__.py
pyhyperminhash/__init__.pyi
pyhyperminhash/py.typed
pyhyperminhash/pyhyperminhash.abi3.so
pyhyperminhash-0.1.5.dist-info/RECORD
