Metadata-Version: 2.4
Name: pyhyperminhash
Version: 0.1.5
Classifier: Programming Language :: Rust
Classifier: Programming Language :: Python :: Implementation :: CPython
Classifier: Programming Language :: Python :: Implementation :: PyPy
Classifier: License :: OSI Approved :: MIT License
License-File: LICENSE
Summary: Very fast, constant memory-footprint cardinality approximation, including intersection
Author-email: Lukas Lueg <lukas.lueg@gmail.com>
Requires-Python: >=3.9
Project-URL: Homepage, https://github.com/lukaslueg/pyhyperminhash
